{
  "githubRepo": "ksia-cs",
  "githubToken": "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",
  "githubUserName": "kkk-a11yy",
  "gardenBaseUrl": "",
  "prHistory": [],
  "baseTheme": "dark",
  "theme": "{\"name\": \"default\", \"modes\": [\"dark\"]}",
  "faviconPath": "",
  "noteSettingsIsInitialized": true,
  "siteName": "Digital Garden",
  "slugifyEnabled": true,
  "noteIconKey": "dg-note-icon",
  "defaultNoteIcon": "",
  "showNoteIconOnTitle": false,
  "showNoteIconInFileTree": false,
  "showNoteIconOnInternalLink": false,
  "showNoteIconOnBackLink": false,
  "showCreatedTimestamp": false,
  "createdTimestampKey": "dg-created",
  "showUpdatedTimestamp": false,
  "updatedTimestampKey": "dg-updated",
  "timestampFormat": "MMM dd, yyyy h:mm a",
  "styleSettingsCss": "",
  "pathRewriteRules": "",
  "customFilters": [],
  "contentClassesKey": "dg-content-classes",
  "defaultNoteSettings": {
    "dgHomeLink": true,
    "dgPassFrontmatter": false,
    "dgShowBacklinks": false,
    "dgShowLocalGraph": false,
    "dgShowInlineTitle": false,
    "dgShowFileTree": false,
    "dgEnableSearch": false,
    "dgShowToc": false,
    "dgLinkPreview": false,
    "dgShowTags": false
  }
}